qibojit/__init__.py
qibojit/backends/__init__.py
qibojit/backends/clifford_operations_cpu.py
qibojit/backends/clifford_operations_gpu.py
qibojit/backends/cpu.py
qibojit/backends/gpu.py
qibojit/backends/matrices.py
qibojit/custom_operators/__init__.py
qibojit/custom_operators/gates.py
qibojit/custom_operators/ops.py
qibojit/custom_operators/raw_kernels.py
qibojit-0.1.12.dist-info/METADATA
qibojit-0.1.12.dist-info/WHEEL
qibojit-0.1.12.dist-info/licenses/LICENSE
qibojit-0.1.12.dist-info/RECORD
