Metadata-Version: 2.4
Name: qibojit
Version: 0.1.12
Summary: Simulation tools based on numba and cupy.
License: Apache-2.0
License-File: LICENSE
Author: The Qibo team
Requires-Python: >=3.10,<3.14
Classifier: License :: OSI Approved :: Apache Software License
Classifier: Programming Language :: Python :: 3
Classifier: Programming Language :: Python :: 3.10
Classifier: Programming Language :: Python :: 3.11
Classifier: Programming Language :: Python :: 3.12
Classifier: Programming Language :: Python :: 3.13
Classifier: Topic :: Scientific/Engineering :: Physics
Provides-Extra: cupy
Provides-Extra: cuquantum
Requires-Dist: cupy-cuda12x (>=13.1.0,<14.0.0) ; extra == "cupy"
Requires-Dist: cuquantum-python-cu12 (>=24.1.0,<25.0.0) ; extra == "cuquantum"
Requires-Dist: numba (>=0.61.0,<0.62.0)
Requires-Dist: psutil (>=5.9.5,<6.0.0)
Requires-Dist: qibo (>=0.2.21,<0.3.0)
Requires-Dist: scipy (>=1.10.1,<2.0.0)
Project-URL: Documentation, https://qibo.science/docs/qibo/stable
Project-URL: Homepage, https://qibo.science
Project-URL: Repository, https://github.com/qiboteam/qibojit
